{"睱": ["竖", "横折", "横", "横", "横", "横折", "横", "竖", "横", "横", "横折", "横", "横撇/横钩", "捺"]}
{"睴": ["竖", "横折", "横", "横", "横", "点", "横撇/横钩", "横", "竖", "横折", "横", "横", "横", "竖"]}
{"睺": ["竖", "横折", "横", "横", "横", "撇", "竖", "横撇/横钩", "横", "撇", "横", "横", "撇", "捺"]}
{"睻": ["竖", "横折", "横", "横", "横", "点", "点", "横撇/横钩", "横", "竖", "横折", "横", "横", "横"]}
{"睽": ["竖", "横折", "横", "横", "横", "横撇/横钩", "点", "撇", "撇", "捺", "横", "横", "撇", "点"]}
{"睿": ["竖", "横", "点", "横撇/横钩", "横", "撇", "点", "撇", "捺", "竖", "横折", "横", "横", "横"]}
{"瞀": ["横撇/横钩", "点", "横撇/横钩", "竖钩", "撇", "撇", "横", "撇", "捺", "竖", "横折", "横", "横", "横"]}
{"瞂": ["撇", "撇", "横", "竖", "竖", "横折", "横", "横", "横", "横", "撇", "横撇/横钩", "捺", "点"]}
{"瞉": ["横", "竖", "横", "点", "横撇/横钩", "横", "竖", "横折", "横", "横", "横", "撇", "横折折/横折弯", "横撇/横钩", "捺"]}
{"瞍": ["竖", "横折", "横", "横", "横", "撇", "竖", "横", "横折", "横", "横", "竖", "横撇/横钩", "捺"]}
{"瞎": ["竖", "横折", "横", "横", "横", "点", "点", "横撇/横钩", "横", "横", "横", "竖", "竖", "横折", "横"]}
{"瞑": ["竖", "横折", "横", "横", "横", "点", "横撇/横钩", "竖", "横折", "横", "横", "点", "横", "撇", "点"]}
{"瞖": ["横", "撇", "横", "横", "撇", "点", "竖折/竖弯", "撇", "横折折/横折弯", "横撇/横钩", "捺", "竖", "横折", "横", "横", "横"]}
{"瞘": ["竖", "横折", "横", "横", "横", "横", "竖", "横折", "横", "竖", "横折", "横", "竖", "横折", "横", "竖折/竖弯"]}
{"瞚": ["竖", "横折", "横", "横", "横", "点", "点", "横撇/横钩", "横", "竖", "横折", "横", "竖", "横", "撇", "点"]}
{"瞝": ["竖", "横折", "横", "横", "横", "点", "横", "撇", "点", "竖折/竖弯", "竖", "竖", "横折钩", "撇折", "点"]}
{"瞠": ["竖", "横折", "横", "横", "横", "竖", "点", "撇", "点", "横撇/横钩", "竖", "横折", "横", "横", "竖", "横"]}
{"瞢": ["横", "竖", "竖", "竖", "横折", "竖", "竖", "横", "点", "横撇/横钩", "竖", "横折", "横", "横", "横"]}
{"瞪": ["竖", "横折", "横", "横", "横", "横撇/横钩", "点", "撇", "撇", "捺", "横", "竖", "横折", "横", "点", "撇", "横"]}
{"瞬": ["竖", "横折", "横", "横", "横", "撇", "点", "点", "撇", "点", "横撇/横钩", "撇", "横撇/横钩", "点", "横", "撇折", "竖"]}
